nexus_e_interface/__init__.py
nexus_e_interface/ontology.py
nexus_e_interface/plugin.py
nexus_e_interface/py.typed
nexus_e_interface/scenario.py
nexus_e_interface/tables.py
nexus_e_interface-0.0.3.dist-info/METADATA
nexus_e_interface-0.0.3.dist-info/WHEEL
nexus_e_interface-0.0.3.dist-info/licenses/LICENSE
nexus_e_interface-0.0.3.dist-info/RECORD
