Metadata-Version: 2.4
Name: nexus-e-interface
Version: 0.0.3
Author-email: Matthieu Boubat <mboubat@ethz.ch>
License-File: LICENSE
Requires-Python: >=3.9.15
Requires-Dist: mysqlclient>=2.2.7
Requires-Dist: sqlalchemy>=2.0.39
